 <test name="bifs-2D-painting-xlineproperties-cap" result="OK" date="07/06/2016 10:18:44">

  <stat subtest="" execution_status="OK" return_status="0" mem_total_avg="0" mem_resident_avg="0" mem_resident_max="45744128" cpu_percent="10%" cpu_elapsed_time="0:00.47" cpu_user_time="0.01" cpu_kernel_time="0.03" page_faults="0" file_inputs="0" socket_msg_rec="0" socket_msg_sent="0" return_value="0">
   <command_line>MP4Box -noprog -for-test  -mem-track -mp4 /Users/travis/build/nguyen-viet-thanh-trung/gpac/tests/media/bifs/bifs-2D-painting-xlineproperties-cap.bt</command_line>
  </stat>
  <stat subtest="" execution_status="OK" return_status="0" mem_total_avg="0" mem_resident_avg="0" mem_resident_max="44433408" cpu_percent="16%" cpu_elapsed_time="0:00.29" cpu_user_time="0.01" cpu_kernel_time="0.03" page_faults="0" file_inputs="0" socket_msg_rec="0" socket_msg_sent="0" return_value="0">
   <command_line>MP4Box -noprog -for-test  -mem-track -xmt /Users/travis/build/nguyen-viet-thanh-trung/gpac/tests/media/bifs/bifs-2D-painting-xlineproperties-cap.bt</command_line>
  </stat>
  <stat subtest="" execution_status="OK" return_status="0" mem_total_avg="0" mem_resident_avg="0" mem_resident_max="45006848" cpu_percent="3%" cpu_elapsed_time="0:01.31" cpu_user_time="0.01" cpu_kernel_time="0.03" page_faults="0" file_inputs="0" socket_msg_rec="0" socket_msg_sent="0" return_value="0">
   <command_line>MP4Box -noprog -for-test  -mem-track -bt /Users/travis/build/nguyen-viet-thanh-trung/gpac/tests/media/bifs/bifs-2D-painting-xlineproperties-cap.mp4 -out test2.bt</command_line>
  </stat>
  <stat subtest="" execution_status="OK" return_status="0" mem_total_avg="0" mem_resident_avg="0" mem_resident_max="45006848" cpu_percent="4%" cpu_elapsed_time="0:01.26" cpu_user_time="0.01" cpu_kernel_time="0.03" page_faults="0" file_inputs="0" socket_msg_rec="0" socket_msg_sent="0" return_value="0">
   <command_line>MP4Box -noprog -for-test  -mem-track -xmt /Users/travis/build/nguyen-viet-thanh-trung/gpac/tests/media/bifs/bifs-2D-painting-xlineproperties-cap.mp4 -out test.xmt</command_line>
  </stat>
  <stat subtest="" execution_status="OK" return_status="0" mem_total_avg="0" mem_resident_avg="0" mem_resident_max="44531712" cpu_percent="3%" cpu_elapsed_time="0:01.29" cpu_user_time="0.01" cpu_kernel_time="0.03" page_faults="0" file_inputs="0" socket_msg_rec="0" socket_msg_sent="0" return_value="0">
   <command_line>MP4Box -noprog -for-test  -mem-track -stat /Users/travis/build/nguyen-viet-thanh-trung/gpac/tests/media/bifs/bifs-2D-painting-xlineproperties-cap.mp4 -std</command_line>
  </stat>
  <stat subtest="" execution_status="OK" return_status="0" mem_total_avg="0" mem_resident_avg="0" mem_resident_max="44613632" cpu_percent="4%" cpu_elapsed_time="0:01.15" cpu_user_time="0.01" cpu_kernel_time="0.03" page_faults="0" file_inputs="0" socket_msg_rec="0" socket_msg_sent="0" return_value="0">
   <command_line>MP4Box -noprog -for-test  -mem-track -stats /Users/travis/build/nguyen-viet-thanh-trung/gpac/tests/media/bifs/bifs-2D-painting-xlineproperties-cap.mp4 -std</command_line>
  </stat>
  <stat subtest="" execution_status="OK" return_status="0" mem_total_avg="0" mem_resident_avg="0" mem_resident_max="44613632" cpu_percent="6%" cpu_elapsed_time="0:00.81" cpu_user_time="0.01" cpu_kernel_time="0.03" page_faults="0" file_inputs="0" socket_msg_rec="0" socket_msg_sent="0" return_value="0">
   <command_line>MP4Box -noprog -for-test  -mem-track -statx /Users/travis/build/nguyen-viet-thanh-trung/gpac/tests/media/bifs/bifs-2D-painting-xlineproperties-cap.mp4 -std</command_line>
  </stat>
  <stat subtest="" execution_status="OK" return_status="0" mem_total_avg="0" mem_resident_avg="0" mem_resident_max="44548096" cpu_percent="8%" cpu_elapsed_time="0:00.59" cpu_user_time="0.01" cpu_kernel_time="0.03" page_faults="0" file_inputs="0" socket_msg_rec="0" socket_msg_sent="0" return_value="0">
   <command_line>MP4Box -noprog -for-test  -mem-track -bt /Users/travis/build/nguyen-viet-thanh-trung/gpac/tests/media/bifs/bifs-2D-painting-xlineproperties-cap.xmt -out test1.bt</command_line>
  </stat>
  <stat subtest="" execution_status="OK" return_status="0" mem_total_avg="0" mem_resident_avg="0" mem_resident_max="45678592" cpu_percent="4%" cpu_elapsed_time="0:01.23" cpu_user_time="0.01" cpu_kernel_time="0.03" page_faults="0" file_inputs="0" socket_msg_rec="0" socket_msg_sent="0" return_value="0">
   <command_line>MP4Box -noprog -for-test  -mem-track -mp4 /Users/travis/build/nguyen-viet-thanh-trung/gpac/tests/media/bifs/bifs-2D-painting-xlineproperties-cap.xmt -out /Users/travis/build/nguyen-viet-thanh-trung/gpac/tests/media/bifs/bifs-2D-painting-xlineproperties-cap.mp4.tmp</command_line>
  </stat>
 </test>
